orbital_mechanics/__init__.py
orbital_mechanics/utils.py
orbital_mechanics-2.0.1.dist-info/LICENSE
orbital_mechanics-2.0.1.dist-info/METADATA
orbital_mechanics-2.0.1.dist-info/WHEEL
orbital_mechanics-2.0.1.dist-info/top_level.txt
orbital_mechanics-2.0.1.dist-info/RECORD
