Metadata-Version: 2.1
Name: orbital-mechanics
Version: 2.0.1
Summary: Python library for calculating orbital data.
Home-page: https://github.com/hyper-expanse/orbital-mechanics
Author: Hutson Betts
Author-email: hutson@hyper-expanse.net
License: Apache License (2.0)
Platform: UNKNOWN
